__init__.py
pywgb/__init__.py
pywgb/_constants.py
pywgb/_deco.py
pywgb/bot/__init__.py
pywgb/bot/_abstract.py
pywgb/bot/_smart.py
pywgb/bot/file.py
pywgb/bot/image.py
pywgb/bot/markdown.py
pywgb/bot/news.py
pywgb/bot/text.py
pywgb/bot/voice.py
pywgb/bot/template_card/__init__.py
pywgb/bot/template_card/news.py
pywgb/bot/template_card/text.py
pywgb-1.0.5.dist-info/licenses/LICENSE
pywgb-1.0.5.dist-info/METADATA
pywgb-1.0.5.dist-info/WHEEL
pywgb-1.0.5.dist-info/top_level.txt
pywgb-1.0.5.dist-info/RECORD
