Metadata-Version: 2.4
Name: pywgb
Version: 1.0.5
Summary: Wecom(A.K.A. WeChat Work) Group Bot python API.
Author-email: Rex Zhou <879582094@qq.com>
License: MIT License
Project-URL: Homepage, https://github.com/ChowRex/pywgb
Project-URL: Documentation, https://github.com/ChowRex/pywgb#readme
Classifier: Programming Language :: Python :: 3
Classifier: License :: OSI Approved :: MIT License
Requires-Python: <3.13,>=3.8
License-File: LICENSE
Requires-Dist: requests>=2.25.0
Requires-Dist: jmespath>=1.0.1
Provides-Extra: all
Requires-Dist: pydub; extra == "all"
Provides-Extra: test
Requires-Dist: pytest; extra == "test"
Requires-Dist: pytest-cov; extra == "test"
Requires-Dist: coverage; extra == "test"
Requires-Dist: pylint; extra == "test"
Requires-Dist: python-dotenv; extra == "test"
Requires-Dist: pydub; extra == "test"
Requires-Dist: pyyaml; extra == "test"
Provides-Extra: build
Requires-Dist: build; extra == "build"
Requires-Dist: twine; extra == "build"
Provides-Extra: docs
Requires-Dist: sphinx>=7.0.0; extra == "docs"
Requires-Dist: sphinx-rtd-theme>=2.0.0; extra == "docs"
Dynamic: license-file
